kivymd_admin/__init__.py
kivymd_admin/cli.py
kivymd_admin/utils.py
kivymd_admin/templates/main.py
kivymd_admin/templates/core/main_router.py
kivymd_admin/templates/screen_template/models.py
kivymd_admin/templates/screen_template/screen.py
kivymd_admin/templates/screen_template/views.py
kivymd_admin-0.0.1.dist-info/LICENSE
kivymd_admin-0.0.1.dist-info/METADATA
kivymd_admin-0.0.1.dist-info/WHEEL
kivymd_admin-0.0.1.dist-info/entry_points.txt
kivymd_admin-0.0.1.dist-info/top_level.txt
kivymd_admin-0.0.1.dist-info/RECORD
