Metadata-Version: 2.2
Name: kivymd-admin
Version: 0.0.1
Summary: A command-line tool for managing KivyMD projects.
Home-page: https://github.com/jangita/kivymd-admin
Author: Chris Ochieng
Author-email: mail@chrisochieng.com
Classifier: Development Status :: 1 - Planning
Classifier: Programming Language :: Python :: 3
Classifier: Operating System :: OS Independent
Classifier: Topic :: Software Development :: Build Tools
Classifier: Natural Language :: English
Classifier: Environment :: Console
Classifier: Intended Audience :: Developers
Requires-Python: >=3.7
License-File: LICENSE
Requires-Dist: kivy>=2.1.0
Requires-Dist: kivymd>=1.1.1
Dynamic: author
Dynamic: author-email
Dynamic: classifier
Dynamic: description
Dynamic: description-content-type
Dynamic: home-page
Dynamic: requires-dist
Dynamic: requires-python
Dynamic: summary
